marzbanapilib/__init__.py
marzbanapilib/__main__.py
marzbanapilib/marzban.py
marzbanapilib/py.typed
marzbanapilib/utils.py
marzbanapilib/sections/__init__.py
marzbanapilib/sections/admin.py
marzbanapilib/sections/base.py
marzbanapilib/sections/core.py
marzbanapilib/sections/node.py
marzbanapilib/sections/system.py
marzbanapilib/sections/user.py
marzbanapilib-0.2.0.dist-info/licenses/LICENSE
marzbanapilib-0.2.0.dist-info/METADATA
marzbanapilib-0.2.0.dist-info/WHEEL
marzbanapilib-0.2.0.dist-info/top_level.txt
marzbanapilib-0.2.0.dist-info/RECORD
