Metadata-Version: 2.4
Name: marzbanapilib
Version: 0.2.0
Summary: A modern async Python client library for Marzban VPN panel API
Home-page: https://github.com/DeepPythonist/marzbanapilib
Author: Mohammad Rasol Esfandiari
Author-email: Mohammad Rasol Esfandiari <mrasolesfandiari@gmail.com>
License: MIT License
Project-URL: Homepage, https://github.com/DeepPythonist/marzbanapilib
Project-URL: Bug Tracker, https://github.com/DeepPythonist/marzbanapilib/issues
Project-URL: Documentation, https://github.com/DeepPythonist/marzbanapilib#readme
Project-URL: Source Code, https://github.com/DeepPythonist/marzbanapilib
Keywords: marzban,vpn,api,client,async
Classifier: Development Status :: 4 - Beta
Classifier: Intended Audience :: Developers
Classifier: License :: OSI Approved :: MIT License
Classifier: Operating System :: OS Independent
Classifier: Programming Language :: Python :: 3
Classifier: Programming Language :: Python :: 3.7
Classifier: Programming Language :: Python :: 3.8
Classifier: Programming Language :: Python :: 3.9
Classifier: Programming Language :: Python :: 3.10
Classifier: Programming Language :: Python :: 3.11
Classifier: Programming Language :: Python :: 3.12
Classifier: Topic :: Internet :: WWW/HTTP
Classifier: Topic :: Software Development :: Libraries :: Python Modules
Classifier: Framework :: AsyncIO
Requires-Python: >=3.7
License-File: LICENSE
Requires-Dist: httpx>=0.24.0
Requires-Dist: pydantic>=2.0.0
Requires-Dist: aiofiles>=23.0.0
Provides-Extra: dev
Requires-Dist: pytest>=7.0; extra == "dev"
Requires-Dist: pytest-asyncio>=0.21.0; extra == "dev"
Requires-Dist: black>=23.0; extra == "dev"
Requires-Dist: isort>=5.0; extra == "dev"
Requires-Dist: mypy>=1.0; extra == "dev"
Requires-Dist: flake8>=6.0; extra == "dev"
Dynamic: license-file
